pypi_mobans_pkg/__init__.py
pypi_mobans_pkg/_version.py
pypi_mobans_pkg/resources/yehua.yml
pypi_mobans_pkg/resources/config/data.yml
pypi_mobans_pkg/resources/new-project/static/CHANGELOG.rst
pypi_mobans_pkg/resources/new-project/static/CUSTOM_README.rst
pypi_mobans_pkg/resources/new-project/static/MANIFEST.in
pypi_mobans_pkg/resources/new-project/static/custom_setup.py.jj2
pypi_mobans_pkg/resources/new-project/static/setup.cfg
pypi_mobans_pkg/resources/new-project/static/tests/requirements.txt.jj2
pypi_mobans_pkg/resources/new-project/templates/Makefile
pypi_mobans_pkg/resources/new-project/templates/__init__.py.jj2
pypi_mobans_pkg/resources/new-project/templates/changelog.yml.jj2
pypi_mobans_pkg/resources/new-project/templates/project-moban.yml.jj2
pypi_mobans_pkg/resources/new-project/templates/project.yml.jj2
pypi_mobans_pkg/resources/statics/moban-update.yml
pypi_mobans_pkg/resources/statics/pythonpublish.yml
pypi_mobans_pkg/resources/statics/azure/azure-pipelines.yml
pypi_mobans_pkg/resources/statics/azure/pipelines-steps-macos.yml
pypi_mobans_pkg/resources/statics/azure/pipelines-steps.yml
pypi_mobans_pkg/resources/templates/CHANGELOG.rst.jj2
pypi_mobans_pkg/resources/templates/CONTRIBUTORS.rst.jj2
pypi_mobans_pkg/resources/templates/MANIFEST.in.jj2
pypi_mobans_pkg/resources/templates/Makefile.jj2
pypi_mobans_pkg/resources/templates/Pipfile.jj2
pypi_mobans_pkg/resources/templates/README.rst.jj2
pypi_mobans_pkg/resources/templates/__init__.py.jj2
pypi_mobans_pkg/resources/templates/_version.py.jj2
pypi_mobans_pkg/resources/templates/badges.rst.jj2
pypi_mobans_pkg/resources/templates/conf.py.jj2
pypi_mobans_pkg/resources/templates/format.sh.jj2
pypi_mobans_pkg/resources/templates/gitignore.jj2
pypi_mobans_pkg/resources/templates/installation.rst.jj2
pypi_mobans_pkg/resources/templates/isort.cfg.jj2
pypi_mobans_pkg/resources/templates/lint.script.jj2
pypi_mobans_pkg/resources/templates/min_requirements.txt.jj2
pypi_mobans_pkg-0.1.4.dist-info/LICENSE
pypi_mobans_pkg-0.1.4.dist-info/METADATA
pypi_mobans_pkg-0.1.4.dist-info/WHEEL
pypi_mobans_pkg-0.1.4.dist-info/top_level.txt
pypi_mobans_pkg-0.1.4.dist-info/RECORD
