Metadata-Version: 2.1
Name: pypi-mobans-pkg
Version: 0.1.4
Summary: Scaffolding mobans for your Python project.
Home-page: https://github.com/moremoban/pypi-mobans-pkg
Author: C.W.
Author-email: wangc_2011@hotmail.com
License: public license
Download-URL: https://github.com/moremoban/pypi-mobans-pkg/archive/0.1.4.tar.gz
Keywords: python
Platform: UNKNOWN
Classifier: Topic :: Software Development :: Libraries
Classifier: Programming Language :: Python
Classifier: Intended Audience :: Developers
Classifier: Programming Language :: Python :: 2.6
Classifier: Programming Language :: Python :: 2.7
Classifier: Programming Language :: Python :: 3.3
Classifier: Programming Language :: Python :: 3.4
Classifier: Programming Language :: Python :: 3.5
Classifier: Programming Language :: Python :: 3.6
Classifier: Programming Language :: Python :: 3.7
Classifier: Programming Language :: Python :: 3.8
